cs/fstags.py
cs_fstags-20250528.dist-info/entry_points.txt
cs_fstags-20250528.dist-info/WHEEL
cs_fstags-20250528.dist-info/METADATA
cs_fstags-20250528.dist-info/RECORD
